nb_thumb/__init__.py
nb_thumb/_modidx.py
nb_thumb/core.py
nb_thumb/gallery.py
nb_thumb/thumb.py
nb_thumb-0.0.9.dist-info/LICENSE
nb_thumb-0.0.9.dist-info/METADATA
nb_thumb-0.0.9.dist-info/WHEEL
nb_thumb-0.0.9.dist-info/entry_points.txt
nb_thumb-0.0.9.dist-info/top_level.txt
nb_thumb-0.0.9.dist-info/RECORD
