Metadata-Version: 2.1
Name: nb-thumb
Version: 0.0.9
Summary: Extract thumbnails from Jupyter notebooks
Home-page: https://github.com/fastai/nb-thumb
Author: Hamel Husain
Author-email: hamel.husain@gmail.com
License: Apache Software License 2.0
Keywords: nbdev jupyter notebook python
Platform: UNKNOWN
Classifier: Development Status :: 4 - Beta
Classifier: Intended Audience :: Developers
Classifier: Natural Language :: English
Classifier: Programming Language :: Python :: 3.7
Classifier: Programming Language :: Python :: 3.8
Classifier: Programming Language :: Python :: 3.9
Classifier: Programming Language :: Python :: 3.10
Classifier: License :: OSI Approved :: Apache Software License
Requires-Python: >=3.7
License-File: LICENSE
Requires-Dist: fastcore
Requires-Dist: nbformat (>=5.7.0)
Requires-Dist: Pillow (>=9.0.0)
Provides-Extra: dev
